cb_key_stroke/__init__.py
cb_key_stroke/cb_key_stroke.py
cb_key_stroke-1.4.1.dist-info/METADATA
cb_key_stroke-1.4.1.dist-info/WHEEL
cb_key_stroke-1.4.1.dist-info/licenses/LICENSE
cb_key_stroke-1.4.1.dist-info/RECORD
