Metadata-Version: 2.4
Name: cb_key_stroke
Version: 1.4.1
Summary: The python key stroke module to capture a key stroke and do something useful (e.g. terminating an application). It works an all platforms
Project-URL: Homepage, https://github.com/chriesibaum/cb_key_stroke
Project-URL: Documentation, https://chriesibaum.github.io/cb_key_stroke/
Project-URL: Repository, https://github.com/chriesibaum/cb_key_stroke
Author-email: Thomas <Thomas@chriesibaum.dev>
License:                                  Apache License
License-File: LICENSE
Classifier: License :: OSI Approved :: Apache Software License
Classifier: Operating System :: OS Independent
Classifier: Programming Language :: Python :: 3.12
Requires-Python: >=3.12
Requires-Dist: msvcrt; platform_system == 'windows'
Requires-Dist: select; platform_system == 'linux'
Requires-Dist: termios; platform_system == 'linux'
Requires-Dist: tty; platform_system == 'linux'
Provides-Extra: dev
Requires-Dist: autopep8; extra == 'dev'
Requires-Dist: bandit; extra == 'dev'
Requires-Dist: flake8; extra == 'dev'
Requires-Dist: hatch; extra == 'dev'
Requires-Dist: m2r2; extra == 'dev'
Requires-Dist: pycodestyle; extra == 'dev'
Requires-Dist: pylint; extra == 'dev'
Requires-Dist: sphinx; extra == 'dev'
Requires-Dist: sphinx-copybutton; extra == 'dev'
Requires-Dist: sphinx-inline-tabs; extra == 'dev'
Requires-Dist: sphinx-rtd-theme; extra == 'dev'
